{
  "index": 1,
  "upgrade_planner": {
    "item": "upgrade-planner",
    "settings": {
      "mappers": [
        {
          "from": {
            "comparator": "=",
            "name": "inserter",
            "quality": "normal",
            "type": "entity"
          },
          "index": 0,
          "to": {
            "name": "fast-inserter",
            "type": "entity"
          }
        },
        {
          "from": {
            "comparator": "=",
            "name": "assembling-machine-1",
            "quality": "normal",
            "type": "entity"
          },
          "index": 1,
          "to": {
            "name": "assembling-machine-2",
            "type": "entity"
          }
        },
        {
          "from": {
            "comparator": "=",
            "name": "small-electric-pole",
            "quality": "normal",
            "type": "entity"
          },
          "index": 2,
          "to": {
            "name": "medium-electric-pole",
            "type": "entity"
          }
        },
        {
          "from": {
            "comparator": "=",
            "name": "transport-belt",
            "quality": "normal",
            "type": "entity"
          },
          "index": 3,
          "to": {
            "name": "fast-transport-belt",
            "type": "entity"
          }
        },
        {
          "from": {
            "comparator": "=",
            "name": "fast-inserter",
            "quality": "normal",
            "type": "entity"
          },
          "index": 4,
          "to": {
            "name": "bulk-inserter",
            "type": "entity"
          }
        },
        {
          "from": {
            "comparator": "=",
            "name": "assembling-machine-2",
            "quality": "normal",
            "type": "entity"
          },
          "index": 5,
          "to": {
            "name": "assembling-machine-3",
            "type": "entity"
          }
        },
        {
          "from": {
            "comparator": "=",
            "name": "splitter",
            "quality": "normal",
            "type": "entity"
          },
          "index": 7,
          "to": {
            "name": "fast-splitter",
            "type": "entity"
          }
        },
        {
          "from": {
            "comparator": "=",
            "name": "underground-belt",
            "quality": "normal",
            "type": "entity"
          },
          "index": 11,
          "to": {
            "name": "fast-underground-belt",
            "type": "entity"
          }
        }
      ]
    },
    "version": 562949957353472
  }
}